{"currencies": [{"Last updated": "15/12/2025", "US Dollar": "47.3986", "Euro": "55.6887", "Pound Sterling": "63.4383", "Canadian Dollar": "34.4317", "Danish Krone": "7.4548", "Norwegian Krone": "4.6753", "Swedish Krona": "5.1031", "Swiss Franc": "59.5535", "Japanese Yen 100": "30.5975", "Saudi Riyal": "12.6319", "Kuwaiti Dinar": "154.4332", "UAE Dirham": "12.9046", "Australian Dollar": "31.5201", "Bahraini Dinar": "125.7192", "Omani Riyal": "123.1070", "Qatari Riyal": "13.0059", "Jordanian Dinar": "66.7587", "Chinese Yuan": "6.7260"}]}