{"currencies": [{"Last updated": "28/05/2024", "US Dollar": "47.4502", "Euro": "51.6116", "Pound Sterling": "60.6271", "Canadian Dollar": "34.8156", "Danish Krone": "6.9179", "Norwegian Krone": "4.5255", "Swedish Krona": "4.5038", "Swiss Franc": "52.0916", "Japanese Yen 100": "30.2423", "Saudi Riyal": "12.6514", "Kuwaiti Dinar": "154.7071", "UAE Dirham": "12.9172", "Australian Dollar": "31.6066", "Bahraini Dinar": "125.8560", "Omani Riyal": "123.2473", "Qatari Riyal": "13.0143", "Jordanian Dinar": "66.9067", "Chinese Yuan": "6.5488"}]}