{"currencies": [{"Last updated": "25/12/2025", "US Dollar": "47.5315", "Euro": "56.0016", "Pound Sterling": "64.2768", "Canadian Dollar": "34.7478", "Danish Krone": "7.4927", "Norwegian Krone": "4.7294", "Swedish Krona": "5.1674", "Swiss Franc": "60.3268", "Japanese Yen 100": "30.4963", "Saudi Riyal": "12.6724", "Kuwaiti Dinar": "154.6593", "UAE Dirham": "12.9397", "Australian Dollar": "31.8366", "Bahraini Dinar": "125.9779", "Omani Riyal": "123.4455", "Qatari Riyal": "13.0348", "Jordanian Dinar": "66.9457", "Chinese Yuan": "6.7844"}]}