{"currencies": [{"Last updated": "19/08/2024", "US Dollar": "48.7159", "Euro": "53.7580", "Pound Sterling": "63.0870", "Canadian Dollar": "35.6006", "Danish Krone": "7.2048", "Norwegian Krone": "4.5710", "Swedish Krona": "4.6741", "Swiss Franc": "56.2929", "Japanese Yen 100": "33.2804", "Saudi Riyal": "12.9819", "Kuwaiti Dinar": "159.3323", "UAE Dirham": "13.2622", "Australian Dollar": "32.5860", "Bahraini Dinar": "129.2541", "Omani Riyal": "126.5248", "Qatari Riyal": "13.3560", "Jordanian Dinar": "68.6139", "Chinese Yuan": "6.8188"}]}