{"currencies": [{"Last updated": "17/03/2026", "US Dollar": "52.2923", "Euro": "60.1780", "Pound Sterling": "69.6742", "Canadian Dollar": "38.1640", "Danish Krone": "8.0528", "Norwegian Krone": "5.4234", "Swedish Krona": "5.6101", "Swiss Franc": "66.4704", "Japanese Yen 100": "32.8676", "Saudi Riyal": "13.9249", "Kuwaiti Dinar": "170.4164", "UAE Dirham": "14.2354", "Australian Dollar": "37.0439", "Bahraini Dinar": "138.4126", "Omani Riyal": "135.8065", "Qatari Riyal": "14.2875", "Jordanian Dinar": "73.6511", "Chinese Yuan": "7.5925"}]}