{"currencies": [{"Last updated": "28/02/2024", "US Dollar": "30.8300", "Euro": "33.3426", "Pound Sterling": "38.9938", "Canadian Dollar": "22.7075", "Danish Krone": "4.4736", "Norwegian Krone": "2.9109", "Swedish Krona": "2.9795", "Swiss Franc": "35.0301", "Japanese Yen 100": "20.4660", "Saudi Riyal": "8.2202", "Kuwaiti Dinar": "100.1266", "UAE Dirham": "8.3928", "Australian Dollar": "20.0395", "Bahraini Dinar": "81.7772", "Omani Riyal": "80.0737", "Qatari Riyal": "8.4524", "Jordanian Dinar": "43.4225", "Chinese Yuan": "4.2824"}]}