{"currencies": [{"Last updated": "24/10/2024", "US Dollar": "48.7263", "Euro": "52.6097", "Pound Sterling": "63.2077", "Canadian Dollar": "35.2552", "Danish Krone": "7.0536", "Norwegian Krone": "4.4573", "Swedish Krona": "4.6096", "Swiss Franc": "56.2854", "Japanese Yen 100": "32.0905", "Saudi Riyal": "12.9726", "Kuwaiti Dinar": "158.9919", "UAE Dirham": "13.2650", "Australian Dollar": "32.4322", "Bahraini Dinar": "129.2302", "Omani Riyal": "126.5617", "Qatari Riyal": "13.3606", "Jordanian Dinar": "68.6285", "Chinese Yuan": "6.8479"}]}