{"currencies": [{"Last updated": "23/12/2025", "US Dollar": "47.4660", "Euro": "55.9909", "Pound Sterling": "64.0933", "Canadian Dollar": "34.6214", "Danish Krone": "7.4951", "Norwegian Krone": "4.7170", "Swedish Krona": "5.1711", "Swiss Franc": "60.2666", "Japanese Yen 100": "30.4347", "Saudi Riyal": "12.6549", "Kuwaiti Dinar": "154.5017", "UAE Dirham": "12.9226", "Australian Dollar": "31.7595", "Bahraini Dinar": "125.8644", "Omani Riyal": "123.2819", "Qatari Riyal": "13.0204", "Jordanian Dinar": "66.8535", "Chinese Yuan": "6.7534"}]}