{"currencies": [{"Last updated": "28/04/2026", "US Dollar": "52.7832", "Euro": "61.7194", "Pound Sterling": "71.1729", "Canadian Dollar": "38.6294", "Danish Krone": "8.2589", "Norwegian Krone": "5.6740", "Swedish Krona": "5.6937", "Swiss Franc": "66.8565", "Japanese Yen 100": "33.0639", "Saudi Riyal": "14.0725", "Kuwaiti Dinar": "172.2409", "UAE Dirham": "14.3698", "Australian Dollar": "37.8139", "Bahraini Dinar": "139.8601", "Omani Riyal": "137.0886", "Qatari Riyal": "14.4786", "Jordanian Dinar": "74.3426", "Chinese Yuan": "7.7207"}]}