{"currencies": [{"Last updated": "23/06/2025", "US Dollar": "50.6196", "Euro": "58.0202", "Pound Sterling": "67.7138", "Canadian Dollar": "36.7021", "Danish Krone": "7.7787", "Norwegian Krone": "4.9672", "Swedish Krona": "5.1960", "Swiss Franc": "61.8217", "Japanese Yen 100": "34.2070", "Saudi Riyal": "13.4903", "Kuwaiti Dinar": "165.1590", "UAE Dirham": "13.7827", "Australian Dollar": "32.2902", "Bahraini Dinar": "134.1271", "Omani Riyal": "131.4623", "Qatari Riyal": "13.8745", "Jordanian Dinar": "71.2952", "Chinese Yuan": "7.0419"}]}