{"currencies": [{"Last updated": "07/03/2024", "US Dollar": "49.3347", "Euro": "53.7502", "Pound Sterling": "62.9215", "Canadian Dollar": "36.5442", "Danish Krone": "7.2104", "Norwegian Krone": "4.7135", "Swedish Krona": "4.7976", "Swiss Franc": "56.0749", "Japanese Yen 100": "33.3771", "Saudi Riyal": "13.1535", "Kuwaiti Dinar": "160.5164", "UAE Dirham": "13.4306", "Australian Dollar": "32.5806", "Bahraini Dinar": "130.8648", "Omani Riyal": "128.1355", "Qatari Riyal": "13.5256", "Jordanian Dinar": "69.4855", "Chinese Yuan": "6.8539"}]}